combadge/__init__.py
combadge/_helpers/__init__.py
combadge/_helpers/dataclasses.py
combadge/_helpers/pydantic.py
combadge/_helpers/typing.py
combadge/core/__init__.py
combadge/core/backend.py
combadge/core/binder.py
combadge/core/errors.py
combadge/core/interfaces.py
combadge/core/markers/__init__.py
combadge/core/markers/base.py
combadge/core/markers/method.py
combadge/core/markers/parameter.py
combadge/core/markers/response.py
combadge/core/response.py
combadge/core/service.py
combadge/core/signature.py
combadge/core/typevars.py
combadge/py.typed
combadge/support/__init__.py
combadge/support/http/__init__.py
combadge/support/http/abc/__init__.py
combadge/support/http/abc/containers.py
combadge/support/http/abc/interfaces.py
combadge/support/http/markers/__init__.py
combadge/support/http/markers/request.py
combadge/support/http/markers/response.py
combadge/support/http/request.py
combadge/support/httpx/__init__.py
combadge/support/httpx/backends/__init__.py
combadge/support/httpx/backends/async_.py
combadge/support/httpx/backends/base.py
combadge/support/httpx/backends/sync.py
combadge/support/shared/__init__.py
combadge/support/shared/request.py
combadge/support/soap/__init__.py
combadge/support/soap/abc.py
combadge/support/soap/markers.py
combadge/support/soap/request.py
combadge/support/soap/response.py
combadge/support/zeep/__init__.py
combadge/support/zeep/backends/__init__.py
combadge/support/zeep/backends/async_.py
combadge/support/zeep/backends/base.py
combadge/support/zeep/backends/sync.py
combadge-4.8.2.dist-info/LICENSE
combadge-4.8.2.dist-info/METADATA
combadge-4.8.2.dist-info/WHEEL
combadge-4.8.2.dist-info/RECORD
