Metadata-Version: 2.1
Name: combadge
Version: 4.8.2
Summary: Generic API client based on Pydantic
Home-page: https://github.com/kpn/combadge
License: Apache-2.0
Keywords: api,api-client,pydantic
Author: Pavel Perestoronin
Author-email: pavel.perestoronin@kpn.com
Requires-Python: >=3.9.0,<4.0.0
Classifier: Development Status :: 5 - Production/Stable
Classifier: Environment :: Web Environment
Classifier: Intended Audience :: Developers
Classifier: License :: OSI Approved :: Apache Software License
Classifier: Programming Language :: Python :: 3
Classifier: Programming Language :: Python :: 3.9
Classifier: Programming Language :: Python :: 3.10
Classifier: Programming Language :: Python :: 3.11
Classifier: Programming Language :: Python :: 3.12
Classifier: Programming Language :: Python :: 3.13
Classifier: Programming Language :: Python :: 3 :: Only
Classifier: Topic :: Internet
Classifier: Topic :: Internet :: WWW/HTTP
Classifier: Topic :: Software Development
Classifier: Topic :: Software Development :: Libraries
Classifier: Topic :: System
Classifier: Topic :: System :: Networking
Classifier: Typing :: Typed
Provides-Extra: httpx
Provides-Extra: zeep
Requires-Dist: get-annotations (>=0.1.2,<0.2.0) ; python_version < "3.10"
Requires-Dist: httpx (>=0.23.3,<1.0.0) ; extra == "httpx"
Requires-Dist: pydantic (>=2.0.0,<3.0.0)
Requires-Dist: typing-extensions (>=4.5.0,<5.0.0)
Requires-Dist: zeep (>=4.2.1,<5.0.0) ; extra == "zeep"
Project-URL: Repository, https://github.com/kpn/combadge
